tracardi_plugin_scaffold/__init__.py
tracardi_plugin_scaffold/create_plugin.py
tracardi_plugin_scaffold/plugin_scaffold.zip
tracardi_scaffold-1.11.dist-info/METADATA
tracardi_scaffold-1.11.dist-info/WHEEL
tracardi_scaffold-1.11.dist-info/entry_points.txt
tracardi_scaffold-1.11.dist-info/top_level.txt
tracardi_scaffold-1.11.dist-info/RECORD
